{
    "lastUpdatedTime": "2026-03-01 10:29:55.815101",
    "ranks": [
        {
            "division": "Division I",
            "mmr": 816,
            "playlist": "1v1 Duel",
            "rank": "Diamond I"
        },
        {
            "division": "Division II",
            "mmr": 1363,
            "playlist": "2v2 Doubles",
            "rank": "Champion III"
        },
        {
            "division": "Division I",
            "mmr": 1069,
            "playlist": "3v3 Standard",
            "rank": "Champion I"
        }
    ]
}